up_SMT_engine/SMTPlanner.py
up_SMT_engine/__init__.py
up_SMT_engine/ProblemBuilder/BaseProblemBuilder.py
up_SMT_engine/ProblemBuilder/ForAllProblemBuilder.py
up_SMT_engine/ProblemBuilder/R2EProblemBuilder.py
up_SMT_engine/ProblemBuilder/ThereExistsProblemBuilder.py
up_SMT_engine/ProblemBuilder/__init__.py
up_SMT_engine/ProblemManager/ProblemManager.py
up_SMT_engine/ProblemManager/__init__.py
up_SMT_engine/actions/BaseAction.py
up_SMT_engine/actions/ForAllAction.py
up_SMT_engine/actions/R2ExistsAction.py
up_SMT_engine/actions/ThereExistsAction.py
up_SMT_engine/actions/__init__.py
up_SMT_engine/fluents/BaseFluent.py
up_SMT_engine/fluents/R2ExistsFluent.py
up_SMT_engine/fluents/__init__.py
up_SMT_engine/helper_functions/FNODEHelperFunctions.py
up_SMT_engine/helper_functions/FluentHelperFunctions.py
up_SMT_engine/helper_functions/IOHelperFunctions.py
up_SMT_engine/helper_functions/ParallelPlanningHelperFunctions.py
up_SMT_engine/helper_functions/PartialOrderPlanFix.py
up_SMT_engine/helper_functions/SmtModelHelperFunctions.py
up_SMT_engine/helper_functions/__init__.py
upSmtEngine-2023.6.27.5.dist-info/LICENSE.txt
upSmtEngine-2023.6.27.5.dist-info/METADATA
upSmtEngine-2023.6.27.5.dist-info/WHEEL
upSmtEngine-2023.6.27.5.dist-info/top_level.txt
upSmtEngine-2023.6.27.5.dist-info/RECORD
