Metadata-Version: 2.1
Name: upSmtEngine
Version: 2023.6.27.5
Summary: Engine for unified-planning, implementing a SMT solver.
Author-email: Ben Pathak <pathak.ban@gmail.com>
License: MIT License
Project-URL: Repository, https://gitlab.com/BPat123/up-smt-engine
Requires-Python: >=3.7
License-File: LICENSE.txt
Requires-Dist: unified-planning
Requires-Dist: z3-solver
